gcp_simple_pipeline/__init__.py
gcp_simple_pipeline-0.0.1.dist-info/LICENSE
gcp_simple_pipeline-0.0.1.dist-info/METADATA
gcp_simple_pipeline-0.0.1.dist-info/WHEEL
gcp_simple_pipeline-0.0.1.dist-info/top_level.txt
gcp_simple_pipeline-0.0.1.dist-info/RECORD
