Metadata-Version: 2.1
Name: gcp-simple-pipeline
Version: 0.0.1
Summary: A simple GCP Python pipeline
Home-page: https://gcp-simple-pipeline.readthedocs.io/
Author: Alessandra Bilardi
Author-email: alessandra.bilardi@gmail.com
License: UNKNOWN
Project-URL: Source, https://github.com/bilardi/gcp-simple-pipeline
Project-URL: Bug Reports, https://github.com/bilardi/gcp-simple-pipeline/issues
Project-URL: Funding, https://donate.pypi.org
Platform: UNKNOWN
Classifier: Programming Language :: Python :: 3
Classifier: License :: OSI Approved :: MIT License
Classifier: Operating System :: OS Independent
Requires-Python: >=3.6
